wgba/__init__.py
wgba/cli.py
wgba/formats.py
wgba/genomes.py
wgba/sizes/__init__.py
wgba/sizes/grch38.chrom.sizes
wgba/sizes/hg19.chrom.sizes
wgba-1.0.dist-info/METADATA
wgba-1.0.dist-info/WHEEL
wgba-1.0.dist-info/entry_points.txt
wgba-1.0.dist-info/top_level.txt
wgba-1.0.dist-info/RECORD
