Metadata-Version: 2.1
Name: wgba
Version: 1.0
Summary: Which genome build again?
Home-page: https://github.com/Chris1221/wgba
Author: Chris Cole
Author-email: ccole@well.ox.ac.uk
License: UNKNOWN
Project-URL: Bug Tracker, https://github.com/Chris1221/wgba/issues
Project-URL: Source, https://github.com/Chris1221/wgba
Platform: UNKNOWN
Requires-Python: >3.6
Requires-Dist: pyBigWig
Requires-Dist: pandas
